{
    "$ref": "#/definitions/Badge",
    "$schema": "http://json-schema.org/draft-07/schema#",
    "definitions": {
        "Badge": {
            "additionalProperties": false,
            "properties": {
                "icon": {
                    "title": "icon",
                    "type": "string"
                },
                "label": {
                    "title": "label",
                    "type": "string"
                },
                "url": {
                    "title": "url",
                    "type": "string"
                }
            },
            "required": [
                "label"
            ],
            "type": "object"
        }
    }
}